LICENSE.txt
MANIFEST.in
README.md
requirements.txt
setup.cfg
setup.py
falcon_autocrud/__init__.py
falcon_autocrud/auth.py
falcon_autocrud/db_session.py
falcon_autocrud/middleware.py
falcon_autocrud/resource.py
falcon_autocrud/schema.py
falcon_autocrud/test.py
falcon_autocrud/test_after_methods.py
falcon_autocrud/test_auth.py
falcon_autocrud/test_base.py
falcon_autocrud/test_before_methods.py
falcon_autocrud/test_collection_patch.py
falcon_autocrud/test_delete.py
falcon_autocrud/test_fields.py
falcon_autocrud/test_fixtures.py
falcon_autocrud/test_join.py
falcon_autocrud/test_meta.py
falcon_autocrud/test_methods.py
falcon_autocrud/test_middleware.py
falcon_autocrud/test_modify_patch.py
falcon_autocrud/test_preconditions.py
falcon_autocrud/test_property.py
falcon_autocrud/test_schema.py
falcon_autocrud/test_serialize.py
falcon_autocrud/test_sort.py
falcon_autocrud/test_subresource.py
falcon_autocrud/test_types.py
falcon_autocrud.egg-info/PKG-INFO
falcon_autocrud.egg-info/SOURCES.txt
falcon_autocrud.egg-info/dependency_links.txt
falcon_autocrud.egg-info/not-zip-safe
falcon_autocrud.egg-info/requires.txt
falcon_autocrud.egg-info/top_level.txt