Metadata-Version: 1.1
Name: falcon-autocrud
Version: 1.0.37
Summary: Makes RESTful CRUD easier
Home-page: https://bitbucket.org/garymonson/falcon-autocrud
Author: Gary Monson
Author-email: gary.monson@gmail.com
License: MIT
Keywords: falcon crud rest database
Platform: UNKNOWN
Classifier: Development Status :: 4 - Beta
Classifier: Intended Audience :: Developers
Classifier: License :: OSI Approved :: MIT License
Classifier: Programming Language :: Python :: 3
Classifier: Programming Language :: Python :: 3.4
Classifier: Topic :: Database :: Front-Ends
Classifier: Topic :: Internet :: WWW/HTTP
Classifier: Topic :: Internet :: WWW/HTTP :: Dynamic Content
Classifier: Topic :: Internet :: WWW/HTTP :: WSGI :: Middleware
